rbcl-1.1.2.data/purelib/rbcl/__init__.py
rbcl-1.1.2.data/purelib/rbcl/_sodium.py
rbcl-1.1.2.data/purelib/rbcl/_sodium.tmpl
rbcl-1.1.2.data/purelib/rbcl/_sodium_build.py
rbcl-1.1.2.data/purelib/rbcl/rbcl.py
rbcl-1.1.2.dist-info/LICENSE
rbcl-1.1.2.dist-info/METADATA
rbcl-1.1.2.dist-info/WHEEL
rbcl-1.1.2.dist-info/top_level.txt
rbcl-1.1.2.dist-info/RECORD
