Metadata-Version: 2.1
Name: rbcl
Version: 1.1.2
Summary: Python library that bundles libsodium and provides wrappers for its Ristretto group functions.
Home-page: https://github.com/nthparty/rbcl
Author: Nth Party
Author-email: team@nthparty.com
License: MIT
Requires-Python: >=3.7
License-File: LICENSE
Requires-Dist: barriers~=1.1
Provides-Extra: build
Requires-Dist: setuptools>=77.0; extra == "build"
Requires-Dist: wheel~=0.45; extra == "build"
Requires-Dist: pystache~=0.6; extra == "build"
Requires-Dist: build~=1.3; extra == "build"
Provides-Extra: coveralls
Requires-Dist: coveralls~=4.0; extra == "coveralls"
Provides-Extra: docs
Requires-Dist: sphinx~=7.4; extra == "docs"
Requires-Dist: sphinx-rtd-theme~=3.0; extra == "docs"
Provides-Extra: lint
Requires-Dist: pylint~=3.3.0; extra == "lint"
Provides-Extra: publish
Requires-Dist: build~=1.3; extra == "publish"
Requires-Dist: twine~=4.0; extra == "publish"
Provides-Extra: test
Requires-Dist: pytest~=8.2; extra == "test"
Requires-Dist: pytest-cov~=5.0; extra == "test"
